express_relay_utils/express_relay_client.py
express_relay_utils/openapi_client/models/bid.py
express_relay_utils/openapi_client/models/bid400_response.py
express_relay_utils/openapi_client/models/bid_result.py
express_relay_utils/openapi_client/models/client_message.py
express_relay_utils/openapi_client/models/client_message_one_of.py
express_relay_utils/openapi_client/models/client_message_one_of1.py
express_relay_utils/openapi_client/models/client_message_one_of_params.py
express_relay_utils/openapi_client/models/client_request.py
express_relay_utils/openapi_client/models/error_body_response.py
express_relay_utils/openapi_client/models/opportunity_bid.py
express_relay_utils/openapi_client/models/opportunity_params.py
express_relay_utils/openapi_client/models/opportunity_params_one_of.py
express_relay_utils/openapi_client/models/opportunity_params_v1.py
express_relay_utils/openapi_client/models/opportunity_params_with_metadata.py
express_relay_utils/openapi_client/models/server_result_message.py
express_relay_utils/openapi_client/models/server_result_message_one_of.py
express_relay_utils/openapi_client/models/server_result_message_one_of1.py
express_relay_utils/openapi_client/models/server_result_response.py
express_relay_utils/openapi_client/models/server_update_response.py
express_relay_utils/openapi_client/models/server_update_response_one_of.py
express_relay_utils/openapi_client/models/token_qty.py
express_relay_utils/searcher/examples/simple_searcher.py
express_relay_utils-0.0.1.dist-info/METADATA
express_relay_utils-0.0.1.dist-info/WHEEL
express_relay_utils-0.0.1.dist-info/RECORD
